{
  "LVM": {
    "name": "Las Vegas Monorail",
    "color": "#0B3B8D",
    "backgroundColor": "#0B3B8D",
    "textColor": "#FFFFFF",
    "order": 0,
    "icon": "north-america/usa/lv/LVM.svg"
  },
  "LVGreen": {
    "name": "Green",
    "color": "#008100",
    "backgroundColor": "#004d00",
    "textColor": "#FFFFFF",
    "order": 1,
    "icon": "north-america/usa/lv/LVGreen.png"
  },
  "LVBlue": {
    "name": "Blue",
    "color": "#00309A",
    "backgroundColor": "#001a5c",
    "textColor": "#FFFFFF",
    "order": 2,
    "icon": "north-america/usa/lv/LVBlue.png"
  },
  "LVRed": {
    "name": "Red",
    "color": "#BF2928",
    "backgroundColor": "#7a1817",
    "textColor": "#FFFFFF",
    "order": 3,
    "icon": "north-america/usa/lv/LVRed.png"
  }
}
